scrapy_rabbit/VERSION
scrapy_rabbit/__init__.py
scrapy_rabbit/cmdline.py
scrapy_rabbit/commands/__init__.py
scrapy_rabbit/commands/genspider.py
scrapy_rabbit/commands/startproject.py
scrapy_rabbit/conf/__init__.py
scrapy_rabbit/conf/confer.py
scrapy_rabbit/core/__init__.py
scrapy_rabbit/core/engine.py
scrapy_rabbit/core/run.py
scrapy_rabbit/http/__init__.py
scrapy_rabbit/http/req.py
scrapy_rabbit/rabbitmq/__init__.py
scrapy_rabbit/rabbitmq/rabbit.py
scrapy_rabbit/settings/__init__.py
scrapy_rabbit/settings/default_settings.py
scrapy_rabbit/templates/project/scrapy.cfg
scrapy_rabbit/templates/project/start.py
scrapy_rabbit/templates/project/module/__init__.py
scrapy_rabbit/templates/project/module/items.py.tmpl
scrapy_rabbit/templates/project/module/middlewares.py.tmpl
scrapy_rabbit/templates/project/module/pipelines.py.tmpl
scrapy_rabbit/templates/project/module/settings.py.tmpl
scrapy_rabbit/templates/project/module/conf/__init__.py
scrapy_rabbit/templates/project/module/conf/config.ini
scrapy_rabbit/templates/project/module/libs/__init__.py
scrapy_rabbit/templates/project/module/libs/lib.py
scrapy_rabbit/templates/project/module/spiders/__init__.py
scrapy_rabbit/templates/project/module/test/__init__.py
scrapy_rabbit/templates/spiders/basic.tmpl
scrapy_rabbit/utils/__init__.py
scrapy_rabbit/utils/loadspider.py
scrapy_rabbit/utils/misc.py
scrapy_rabbit/utils/pipelines.py
scrapy_rabbit/utils/project.py
scrapy_rabbit/utils/template.py
test/__init__.py
scrapy_rabbit-0.2.5.dist-info/LICENSE
scrapy_rabbit-0.2.5.dist-info/METADATA
scrapy_rabbit-0.2.5.dist-info/WHEEL
scrapy_rabbit-0.2.5.dist-info/entry_points.txt
scrapy_rabbit-0.2.5.dist-info/top_level.txt
scrapy_rabbit-0.2.5.dist-info/RECORD
