Metadata-Version: 2.1
Name: scrapy-rabbit
Version: 0.2.5
Summary: 在scrapy的基础上进行修改，使用了异步请求，加快采集速度，并与rabbitmq结合，实现了断点续爬，与防止漏采
Home-page: https://elanpy.com
Author: eamonn
Author-email: china.eamonn@gmail.com
License: MIT
Platform: UNKNOWN
Classifier: License :: OSI Approved :: MIT License
Classifier: Programming Language :: Python
Classifier: Programming Language :: Python :: 3
Classifier: Programming Language :: Python :: 3.6
Classifier: Programming Language :: Python :: Implementation :: CPython
Classifier: Programming Language :: Python :: Implementation :: PyPy
Requires-Python: >=3.4.0
Requires-Dist: scrapy
Requires-Dist: pika
Requires-Dist: yarl
Requires-Dist: fuclib
Requires-Dist: aiohttp
